quickcrop/__init__.py
quickcrop/__main__.py
quickcrop/crop.py
quickcrop/gui.py
quickcrop-0.1.2.dist-info/licenses/LICENSE
quickcrop-0.1.2.dist-info/METADATA
quickcrop-0.1.2.dist-info/WHEEL
quickcrop-0.1.2.dist-info/entry_points.txt
quickcrop-0.1.2.dist-info/top_level.txt
quickcrop-0.1.2.dist-info/RECORD
