Metadata-Version: 2.4
Name: quickcrop
Version: 0.1.2
Summary: A minimal GUI app for image cropping
Requires-Python: >=3.14
License-File: LICENSE
Requires-Dist: pillow>=12.0.0
Dynamic: license-file
